{
	"$schema": "./gen/schemas/mobile-schema.json",
	"productName": "RdChat Mobile",
	"version": "0.0.0",
	"identifier": "android.rdchat.ru",
	"build": {
		"frontendDist": "../../fluxer_app/dist"
	},
	"app": {
		"withGlobalTauri": true,
		"windows": [
			{
				"label": "main",
				"title": "RdChat",
				"fullscreen": false,
				"resizable": true
			}
		],
		"security": {
			"csp": null
		}
	},
	"bundle": {
		"active": true,
		"android": {
			"minSdkVersion": 24
		},
		"icon": [
			"../../fluxer_desktop/build_resources/icons-stable/32x32.png",
			"../../fluxer_desktop/build_resources/icons-stable/128x128.png",
			"../../fluxer_desktop/build_resources/icons-stable/512x512.png",
			"../../fluxer_desktop/build_resources/icons-stable/icon.png"
		]
	}
}
